qvatel/__init__.py
qvatel/client.py
qvatel_sms_api-1.0.7.dist-info/METADATA
qvatel_sms_api-1.0.7.dist-info/WHEEL
qvatel_sms_api-1.0.7.dist-info/top_level.txt
qvatel_sms_api-1.0.7.dist-info/RECORD
