Metadata-Version: 2.1
Name: qvatel-sms-api
Version: 1.0.7
Summary: Una librería de Python para enviar SMS a través de QvaTel.com
Home-page: https://github.com/yoandysse/qvatel_sms_api.git
Author: Yoandy Isse
Author-email: yoandysse@gmail.com
License: MIT
Keywords: sms,qvatel,api,python,enviar sms,sms masivos,sms marketing,sms api,sms gateway
Requires-Dist: requests (<3.0.0,>=2.31.0)
